<?xml version="1.0" encoding="utf-8" ?>
<dwsync>
<file name="img1.jpg" server="wcet1.waketech.edu/web111/" local="130342224398867823" remote="130342227600000000" Dst="1" />
<file name="the_keys.psd" server="wcet1.waketech.edu/web111/" local="130363772182971593" remote="130363773600000000" Dst="1" />
<file name="state_fair2.jpg" server="wcet1.waketech.edu/web111/" local="130376603335112800" remote="130376603400000000" Dst="1" />
<file name="state_fair.html" server="wcet1.waketech.edu/web111/" local="130376609715077713" remote="130376609400000000" Dst="1" />
<file name="state_fair.jpg" server="wcet1.waketech.edu/web111/" local="130376602811382844" remote="130376608200000000" Dst="1" />
<file name="elkins_designcomp.html" server="wcet1.waketech.edu/web111/" local="130418906545575170" remote="130418907000000000" Dst="2" />
<file name="elkins_designcomp.pdf" server="wcet1.waketech.edu/web111/" local="130418906937437584" remote="130418908200000000" Dst="2" />
<file name="elkins_designcomp.psd" server="wcet1.waketech.edu/web111/" local="130418904817936355" remote="130418908800000000" Dst="2" />
<file name="elkins-gif.gif" server="wcet1.waketech.edu/web111/" local="130425188529374900" remote="130425190800000000" Dst="2" />
</dwsync>